{"MEET":{"RESULT":{"MEETING":{"NAME":"Newbury","DATE":"09-JUN-2016","COUNTRY":"UK","RANKING":"1","GOING":"GOOD TO FIRM","TOTEPLACEPOT":"Pool - £69,486.97 Winning Units - 118.89 Dividend - £426.60","TOTEQUADPOT":"Pool - £4,444.51 Winning Units - 23.9 Dividend - £137.60","TOTEPLACESIX":"Dividend - £259.59","TOTEPLACEFIVE":"Dividend - £54.69","MULTIBET":["Pool - £69,486.97 Dividend - £426.60 Winning Units - 118.89 ","Pool - £4,444.51 Dividend - £137.60 Winning Units - 23.9 ","Dividend - £259.59 ","Dividend - £54.69 "],"RACES":[{"TIME":"2.00","NAME":"BE WISER INSURANCE NOVICE STAKES (PLUS 10)","DIST":"6f 110ys","VALUE":"£6,250","NORUN":"13","BEATENFAV":"(4)-Dourado 6th, 11/4 fav","DISTANCES":"shd, hd","NONRUNNERS":"6,14","WITHDRAWN":null,"TOTEEXACTA":null,"TOTETRIO":null,"RUNNERS":[{"POSITION":"1","NAME":"Aardwolf","SNO":"1","TRAINER":"Mark Johnston","JOCKEY":"James Doyle","WEIGHT":"9-2","ALLOWANCE":null,"OVERWEIGHT":null,"SP":"5/1","TOTEWIN":"£5.50","TOTEPLACE":"£2.00"},{"POSITION":"2","NAME":"Sea Fox","SNO":"12","TRAINER":"David Evans","JOCKEY":"F M Berry","WEIGHT":"9-2","ALLOWANCE":null,"OVERWEIGHT":null,"SP":"12/1","TOTEWIN":null,"TOTEPLACE":"£3.30"},{"POSITION":"3","NAME":"Ronald R","SNO":"11","TRAINER":"Michael Bell","JOCKEY":"J P Spencer","WEIGHT":"9-2","ALLOWANCE":null,"OVERWEIGHT":null,"SP":"16/1","TOTEWIN":null,"TOTEPLACE":"£3.80"}]},{"TIME":"2.30","NAME":"CROSSLAND EBF STALLIONS MAIDEN FILLIES' STAKES (PLUS 10) (STR)","DIST":"1m","VALUE":"£8,250","NORUN":"13","BEATENFAV":null,"DISTANCES":"0.75L, hd","NONRUNNERS":"10","WITHDRAWN":null,"TOTEEXACTA":null,"TOTETRIO":null,"RUNNERS":[{"POSITION":"1","NAME":"Aghaany","SNO":"1","TRAINER":"Roger Varian","JOCKEY":"Andrea Atzeni","WEIGHT":"9-0","ALLOWANCE":null,"OVERWEIGHT":null,"SP":"6/1","TOTEWIN":"£6.30","TOTEPLACE":"£1.80"},{"POSITION":"2","NAME":"Side Hill","SNO":"12","TRAINER":"John Gosden","JOCKEY":"James Doyle","WEIGHT":"9-0","ALLOWANCE":null,"OVERWEIGHT":null,"SP":"10/3","TOTEWIN":null,"TOTEPLACE":"£1.50"},{"POSITION":"3","NAME":"Volition","SNO":"14","TRAINER":"Sir Michael Stoute","JOCKEY":"R L Moore","WEIGHT":"9-0","ALLOWANCE":null,"OVERWEIGHT":null,"SP":"2/1fav","TOTEWIN":null,"TOTEPLACE":"£1.40"}]},{"TIME":"3.05","NAME":"LORD WEINSTOCK MEMORIAL EBF STALLIONS STAKES (FILLIES' LISTED)","DIST":"1m 2f 6ys","VALUE":"£50,000","NORUN":"7","BEATENFAV":"(7)-Snow Moon 3rd, 10/11 fav","DISTANCES":"0.5L","NONRUNNERS":"6,9","WITHDRAWN":null,"TOTEEXACTA":null,"TOTETRIO":null,"RUNNERS":[{"POSITION":"1","NAME":"Abingdon","SNO":"1","TRAINER":"Sir Michael Stoute","JOCKEY":"R L Moore","WEIGHT":"9-0","ALLOWANCE":null,"OVERWEIGHT":null,"SP":"2/1","TOTEWIN":"£3.00","TOTEPLACE":"£1.60"},{"POSITION":"2","NAME":"Beauly","SNO":"2","TRAINER":"Charles Hills","JOCKEY":"James Doyle","WEIGHT":"9-0","ALLOWANCE":null,"OVERWEIGHT":null,"SP":"9/1","TOTEWIN":null,"TOTEPLACE":"£3.30"}]},{"TIME":"3.40","NAME":"COMAX HANDICAP (STR)","DIST":"1m","VALUE":"£10,000","NORUN":"13","BEATENFAV":null,"DISTANCES":"hd, nk","NONRUNNERS":"10,13","WITHDRAWN":null,"TOTEEXACTA":null,"TOTETRIO":null,"RUNNERS":[{"POSITION":"1","NAME":"Iconic","SNO":"7","TRAINER":"Henry Candy","JOCKEY":"Oisin Murphy","WEIGHT":"9-3","ALLOWANCE":null,"OVERWEIGHT":null,"SP":"25/1","TOTEWIN":"£32.60","TOTEPLACE":"£6.40"},{"POSITION":"2","NAME":"Weld Al Emarat","SNO":"2","TRAINER":"S Crisford","JOCKEY":"J P Spencer","WEIGHT":"9-7","ALLOWANCE":null,"OVERWEIGHT":null,"SP":"7/2fav","TOTEWIN":null,"TOTEPLACE":"£2.20"},{"POSITION":"3","NAME":"Exceeding Power","SNO":"15","TRAINER":"M R Bosley","JOCKEY":"George Wood","WEIGHT":"8-0","ALLOWANCE":"7","OVERWEIGHT":null,"SP":"8/1","TOTEWIN":null,"TOTEPLACE":"£4.10"}]},{"TIME":"4.10","NAME":"BE WISER INSURANCE 'RESTRICTED' HANDICAP","DIST":"7f","VALUE":"£5,000","NORUN":"13","BEATENFAV":null,"DISTANCES":"nk, 2.75L","NONRUNNERS":"2","WITHDRAWN":null,"TOTEEXACTA":null,"TOTETRIO":null,"RUNNERS":[{"POSITION":"1","NAME":"Blackout","SNO":"1","TRAINER":"Richard Hannon","JOCKEY":"P J Dobbs","WEIGHT":"9-7","ALLOWANCE":null,"OVERWEIGHT":null,"SP":"20/1","TOTEWIN":"£20.60","TOTEPLACE":"£5.30"},{"POSITION":"2","NAME":"Generalship","SNO":"7","TRAINER":"John Gosden","JOCKEY":"James Doyle","WEIGHT":"9-4","ALLOWANCE":null,"OVERWEIGHT":null,"SP":"11/4fav","TOTEWIN":null,"TOTEPLACE":"£1.60"},{"POSITION":"3","NAME":"Red Tea","SNO":"9","TRAINER":"P Hiatt","JOCKEY":"F M Berry","WEIGHT":"8-13","ALLOWANCE":null,"OVERWEIGHT":null,"SP":"12/1","TOTEWIN":null,"TOTEPLACE":"£3.60"}]},{"TIME":"4.45","NAME":"INSURE WISER HANDICAP","DIST":"1m 4f 5ys","VALUE":"£5,000","NORUN":"12","BEATENFAV":"(3)-Molten Gold 7th, 4/1 fav","DISTANCES":"0.75L, 1.75L","NONRUNNERS":"7,14","WITHDRAWN":null,"TOTEEXACTA":null,"TOTETRIO":null,"RUNNERS":[{"POSITION":"1","NAME":"Muaither","SNO":"8","TRAINER":"John Gosden","JOCKEY":"L Dettori","WEIGHT":"9-2","ALLOWANCE":null,"OVERWEIGHT":null,"SP":"13/2","TOTEWIN":"£7.50","TOTEPLACE":"£2.70"},{"POSITION":"2","NAME":"Admiral's Sunset","SNO":"5","TRAINER":"H Morrison","JOCKEY":"G Baker","WEIGHT":"9-5","ALLOWANCE":null,"OVERWEIGHT":null,"SP":"8/1","TOTEWIN":null,"TOTEPLACE":"£3.00"},{"POSITION":"3","NAME":"Niceonecenturion","SNO":"4","TRAINER":"William Knight","JOCKEY":"Jim Crowley","WEIGHT":"9-6","ALLOWANCE":null,"OVERWEIGHT":null,"SP":"9/1","TOTEWIN":null,"TOTEPLACE":"£3.60"}]},{"TIME":"5.15","NAME":"WISER ACADEMY AMATEUR RIDERS' HANDICAP","DIST":"1m 2f 6ys","VALUE":"£5,000","NORUN":"12","BEATENFAV":null,"DISTANCES":"3.5L, 2L","NONRUNNERS":"3,5,11","WITHDRAWN":null,"TOTEEXACTA":null,"TOTETRIO":null,"RUNNERS":[{"POSITION":"1","NAME":"Good of Luck","SNO":"13","TRAINER":"W J Greatrex","JOCKEY":"Mr T Greatrex","WEIGHT":"10-2","ALLOWANCE":"3","OVERWEIGHT":null,"SP":"7/1","TOTEWIN":"£7.60","TOTEPLACE":"£2.40"},{"POSITION":"2","NAME":"City Ground","SNO":"7","TRAINER":"M Appleby","JOCKEY":"Miss S Brotherton","WEIGHT":"10-11","ALLOWANCE":null,"OVERWEIGHT":null,"SP":"15/8fav","TOTEWIN":null,"TOTEPLACE":"£1.30"},{"POSITION":"3","NAME":"Silver Alliance","SNO":"8","TRAINER":"Miss J Feilden","JOCKEY":"Mr R Birkett","WEIGHT":"10-10","ALLOWANCE":null,"OVERWEIGHT":null,"SP":"16/1","TOTEWIN":null,"TOTEPLACE":"£4.90"}]}]}}}}