{"MEET":{"RESULT":{"MEETING":{"NAME":"Wolverhampton","DATE":"20-JUN-2016","COUNTRY":"UK","RANKING":"4","GOING":"STANDARD","TOTEPLACEPOT":"Pool - £73,864.34 Winning Units - 3516.78 Dividend - £15.30","TOTEQUADPOT":"Pool - £7,805.63 Winning Units - 1438.57 Dividend - £4.00","TOTEPLACESIX":"Dividend - £23.72","TOTEPLACEFIVE":"Dividend - £3.76","MULTIBET":["Pool - £73,864.34 Dividend - £15.30 Winning Units - 3516.78 ","Pool - £7,805.63 Dividend - £4.00 Winning Units - 1438.57 ","Dividend - £23.72 ","Dividend - £3.76 "],"RACES":[{"TIME":"6.10","NAME":"VISIT ATTHERACES.COM AMATEUR RIDERS' SELLING STAKES","DIST":"1m 4f 50ys","VALUE":"£3,500","NORUN":"12","BEATENFAV":"(9)-Singular Quest 7th, (12)-Kissy Suzuki unseated rider, 3/1 jfav","DISTANCES":"6L, 1.25L","NONRUNNERS":null,"WITHDRAWN":null,"TOTEEXACTA":null,"TOTETRIO":null,"RUNNERS":[{"POSITION":"1","NAME":"Yasir","SNO":"3","TRAINER":"Mrs S Leech","JOCKEY":"Miss C V Hart","WEIGHT":"11-4","ALLOWANCE":null,"OVERWEIGHT":null,"SP":"4/1","TOTEWIN":"£5.20","TOTEPLACE":"£1.60"},{"POSITION":"2","NAME":"Flag Of Glory","SNO":"4","TRAINER":"P Hiatt","JOCKEY":"Miss M Edden","WEIGHT":"10-7","ALLOWANCE":"5","OVERWEIGHT":null,"SP":"50/1","TOTEWIN":null,"TOTEPLACE":"£9.20"},{"POSITION":"2","NAME":"Goal","SNO":"5","TRAINER":"Sally Randell","JOCKEY":"Miss B Hampson","WEIGHT":"10-12","ALLOWANCE":null,"OVERWEIGHT":null,"SP":"20/1","TOTEWIN":null,"TOTEPLACE":"£7.00"}]},{"TIME":"6.40","NAME":"FOLLOW AT ATTHERACES ON TWITTER HANDICAP","DIST":"5f 20ys","VALUE":"£4,800","NORUN":"5","BEATENFAV":null,"DISTANCES":"0.75L","NONRUNNERS":"1,3","WITHDRAWN":null,"TOTEEXACTA":null,"TOTETRIO":null,"RUNNERS":[{"POSITION":"1","NAME":"Black Grass","SNO":"6","TRAINER":"M W Easterby","JOCKEY":"Cameron Hardie","WEIGHT":"9-4","ALLOWANCE":null,"OVERWEIGHT":null,"SP":"10/11fav","TOTEWIN":"£1.80","TOTEPLACE":"£1.10"},{"POSITION":"2","NAME":"Dutch Archer","SNO":"5","TRAINER":"J Gask","JOCKEY":"R Kingscote","WEIGHT":"9-0","ALLOWANCE":null,"OVERWEIGHT":null,"SP":"5/2","TOTEWIN":null,"TOTEPLACE":"£1.70"}]},{"TIME":"7.10","NAME":"DOWNLOAD THE AT THE RACES APP NOVICE STAKES (PLUS 10)","DIST":"5f 216ys","VALUE":"£6,100","NORUN":"9","BEATENFAV":null,"DISTANCES":"2.25L, 8L","NONRUNNERS":null,"WITHDRAWN":null,"TOTEEXACTA":null,"TOTETRIO":null,"RUNNERS":[{"POSITION":"1","NAME":"Jacquard","SNO":"7","TRAINER":"Mark Johnston","JOCKEY":"F Norton","WEIGHT":"9-0","ALLOWANCE":null,"OVERWEIGHT":null,"SP":"10/11fav","TOTEWIN":"£1.70","TOTEPLACE":"£1.10"},{"POSITION":"2","NAME":"Mr Hobbs","SNO":"8","TRAINER":"S Kirk","JOCKEY":"Luke Morris","WEIGHT":"9-0","ALLOWANCE":null,"OVERWEIGHT":null,"SP":"7/4","TOTEWIN":null,"TOTEPLACE":"£1.50"},{"POSITION":"3","NAME":"Billy's Boots","SNO":"4","TRAINER":"A Reid","JOCKEY":"Tom Marquand","WEIGHT":"8-11","ALLOWANCE":"3","OVERWEIGHT":null,"SP":"14/1","TOTEWIN":null,"TOTEPLACE":"£3.10"}]},{"TIME":"7.40","NAME":"JOIN THE BLACK COUNTRY CHAMBER OF COMMERCE CLAIMING STAKES","DIST":"5f 216ys","VALUE":"£4,800","NORUN":"8","BEATENFAV":null,"DISTANCES":"0.5L, 0.5L","NONRUNNERS":null,"WITHDRAWN":null,"TOTEEXACTA":null,"TOTETRIO":null,"RUNNERS":[{"POSITION":"1","NAME":"Broughtons Fancy","SNO":"5","TRAINER":"A Reid","JOCKEY":"Tom Marquand","WEIGHT":"8-5","ALLOWANCE":"3","OVERWEIGHT":null,"SP":"6/5fav","TOTEWIN":"£2.10","TOTEPLACE":"£1.10"},{"POSITION":"2","NAME":"Silver Springs","SNO":"7","TRAINER":"David Evans","JOCKEY":"Philip Prince","WEIGHT":"8-3","ALLOWANCE":"3","OVERWEIGHT":null,"SP":"7/2","TOTEWIN":null,"TOTEPLACE":"£1.50"},{"POSITION":"3","NAME":"Kenstone","SNO":"4","TRAINER":"David Dennis","JOCKEY":"Luke Morris","WEIGHT":"8-9","ALLOWANCE":null,"OVERWEIGHT":null,"SP":"25/1","TOTEWIN":null,"TOTEPLACE":"£3.90"}]},{"TIME":"8.10","NAME":"AT THE RACES SKY 415 HANDICAP","DIST":"7f 32ys","VALUE":"£3,700","NORUN":"12","BEATENFAV":null,"DISTANCES":"nk, 1.75L","NONRUNNERS":null,"WITHDRAWN":null,"TOTEEXACTA":null,"TOTETRIO":null,"RUNNERS":[{"POSITION":"1","NAME":"Illusive Force","SNO":"11","TRAINER":"D Shaw","JOCKEY":"Martin Lane","WEIGHT":"9-5","ALLOWANCE":null,"OVERWEIGHT":null,"SP":"13/2","TOTEWIN":"£11.90","TOTEPLACE":"£3.80"},{"POSITION":"2","NAME":"Orlando Rogue","SNO":"3","TRAINER":"Conor Dore","JOCKEY":"P Mulrennan","WEIGHT":"9-10","ALLOWANCE":null,"OVERWEIGHT":null,"SP":"8/1","TOTEWIN":null,"TOTEPLACE":"£4.50"},{"POSITION":"3","NAME":"Not Your Call","SNO":"2","TRAINER":"L Carter","JOCKEY":"Kieren Fox","WEIGHT":"9-10","ALLOWANCE":null,"OVERWEIGHT":null,"SP":"5/2fav","TOTEWIN":null,"TOTEPLACE":"£1.30"}]},{"TIME":"8.40","NAME":"FOLLOW AT THE RACES ON INSTAGRAM MEDIAN AUCTION MAIDEN STAKES","DIST":"1m 141ys","VALUE":"£4,800","NORUN":"10","BEATENFAV":"(3)-Naqdy 7th, 9/4 fav","DISTANCES":"0.75L, 3L","NONRUNNERS":null,"WITHDRAWN":null,"TOTEEXACTA":null,"TOTETRIO":null,"RUNNERS":[{"POSITION":"1","NAME":"Shadad","SNO":"5","TRAINER":"Ralph Beckett","JOCKEY":"F M Berry","WEIGHT":"9-5","ALLOWANCE":null,"OVERWEIGHT":null,"SP":"4/1","TOTEWIN":"£7.00","TOTEPLACE":"£1.70"},{"POSITION":"2","NAME":"Van Dyke","SNO":"6","TRAINER":"H Morrison","JOCKEY":"Luke Morris","WEIGHT":"9-5","ALLOWANCE":null,"OVERWEIGHT":null,"SP":"11/4","TOTEWIN":null,"TOTEPLACE":"£1.10"},{"POSITION":"3","NAME":"Crystallographer","SNO":"7","TRAINER":"David Lanigan","JOCKEY":"S W Kelly","WEIGHT":"9-0","ALLOWANCE":null,"OVERWEIGHT":null,"SP":"3/1","TOTEWIN":null,"TOTEPLACE":"£2.00"}]},{"TIME":"9.10","NAME":"WATCH TODAY'S REPLAYS ON THE ATR APP HANDICAP","DIST":"1m 141ys","VALUE":"£3,700","NORUN":"8","BEATENFAV":null,"DISTANCES":"1.25L, nk","NONRUNNERS":null,"WITHDRAWN":null,"TOTEEXACTA":null,"TOTETRIO":null,"RUNNERS":[{"POSITION":"1","NAME":"Vastly","SNO":"1","TRAINER":"Mrs S Leech","JOCKEY":"Luke Morris","WEIGHT":"9-7","ALLOWANCE":null,"OVERWEIGHT":null,"SP":"7/2","TOTEWIN":"£3.80","TOTEPLACE":"£1.70"},{"POSITION":"2","NAME":"What Usain","SNO":"3","TRAINER":"David O'Meara","JOCKEY":"D Tudhope","WEIGHT":"9-6","ALLOWANCE":null,"OVERWEIGHT":null,"SP":"9/4fav","TOTEWIN":null,"TOTEPLACE":"£1.40"},{"POSITION":"3","NAME":"Filament Of Gold","SNO":"8","TRAINER":"R Brotherton","JOCKEY":"Gary Mahon","WEIGHT":"8-8","ALLOWANCE":"5","OVERWEIGHT":null,"SP":"7/2","TOTEWIN":null,"TOTEPLACE":"£1.30"}]}]}}}}